roktools/hatanaka.py
roktools/file.py
roktools/rinex.py
roktools/sinex.py
roktools/geodetic.py
roktools/cl.py
roktools/tensorial.py
roktools/time.py
roktools/_c_ext.cpython-311-i386-linux-musl.so
roktools/logger.py
roktools/decorator.py
roktools/stats.py
roktools/__init__.py
roktools/constants.py
roktools/_c_ext/src/mtable_init.c
roktools/_c_ext/src/hatanaka.c
roktools/_c_ext/src/helpers.c
roktools/parsers/rtklib/stats.py
roktools/orbit/kepler.py
roktools/orbit/tle.py
roktools/orbit/__init__.py
roktools/gnss/types.py
roktools/gnss/residuals.py
roktools/gnss/edit.py
roktools/gnss/__init__.py
roktools/gnss/observables.py
roktools-6.10.2.dist-info/LICENSE
roktools-6.10.2.dist-info/WHEEL
roktools-6.10.2.dist-info/RECORD
roktools-6.10.2.dist-info/top_level.txt
roktools-6.10.2.dist-info/entry_points.txt
roktools-6.10.2.dist-info/METADATA
